stashy/__init__.py
stashy/allrepos.py
stashy/branch_permissions.py
stashy/builds.py
stashy/client.py
stashy/compat.py
stashy/diffs.py
stashy/errors.py
stashy/fileinfo.py
stashy/helpers.py
stashy/permissions.py
stashy/projects.py
stashy/pullrequestdiffs.py
stashy/pullrequests.py
stashy/repos.py
stashy/ssh.py
stashy/admin/__init__.py
stashy/admin/groups.py
stashy/admin/users.py
stashy-0.6.dist-info/LICENSE
stashy-0.6.dist-info/METADATA
stashy-0.6.dist-info/WHEEL
stashy-0.6.dist-info/top_level.txt
stashy-0.6.dist-info/RECORD
