Metadata-Version: 1.1
Name: stashy
Version: 0.6
Summary: Python API client for the  Atlassian Bitbucket Server (formerly known as Stash) REST API
Home-page: http://github.com/cosmin/stashy
Author: Cosmin Stejerean
Author-email: cosmin@offbytwo.com
License: Apache License 2.0
Download-URL: https://github.com/cosmin/stashy
Platform: UNKNOWN
Classifier: Development Status :: 3 - Alpha
Classifier: License :: OSI Approved :: Apache Software License
Classifier: Topic :: Software Development :: Libraries
Classifier: Programming Language :: Python :: 2
Classifier: Programming Language :: Python :: 2.6
Classifier: Programming Language :: Python :: 2.7
Classifier: Programming Language :: Python :: 3
Classifier: Programming Language :: Python :: 3.5
Classifier: Programming Language :: Python :: 3.6
Classifier: Programming Language :: Python :: 3.7
